rtl/ram.v
module ram #(
    parameter ADDR_WIDTH = 8,
    parameter DATA_WIDTH = 8,
    parameter DEPTH = 256
)(
    input wire clk,
    input wire wr_en,
    input wire rd_en,
    input wire [ADDR_WIDTH-1:0] addr,
    input wire [DATA_WIDTH-1:0] data_in,
    output reg [DATA_WIDTH-1:0] data_out,
    output reg ready
);

    // Memory array
    reg [DATA_WIDTH-1:0] mem [0:DEPTH-1];
    
    integer i;
    initial begin
        for (i = 0; i < DEPTH; i = i + 1)
            mem[i] = 8'h00;
    end

    always @(posedge clk) begin
        ready <= 0;
        
        if (wr_en) begin
            mem[addr] <= data_in;
            ready <= 1;
        end
        
        if (rd_en) begin
            data_out <= mem[addr];
            ready <= 1;
        end
    end

endmodule

rtl/ram_controller.v
module ram_controller #(
    parameter ADDR_WIDTH = 8,
    parameter DATA_WIDTH = 8
)(
    input wire clk,
    input wire rst,
    
    // User interface
    input wire start,
    input wire rw,              // 0=read, 1=write
    input wire [ADDR_WIDTH-1:0] address,
    input wire [DATA_WIDTH-1:0] write_data,
    output reg [DATA_WIDTH-1:0] read_data,
    output reg done,
    
    // RAM interface
    output reg ram_wr_en,
    output reg ram_rd_en,
    output reg [ADDR_WIDTH-1:0] ram_addr,
    output reg [DATA_WIDTH-1:0] ram_data_in,
    input wire [DATA_WIDTH-1:0] ram_data_out,
    input wire ram_ready
);

    // State machine
    localparam IDLE = 2'b00;
    localparam WRITE = 2'b01;
    localparam READ = 2'b10;
    localparam DONE = 2'b11;
    
    reg [1:0] state, next_state;

    // State register
    always @(posedge clk or posedge rst) begin
        if (rst)
            state <= IDLE;
        else
            state <= next_state;
    end

    // Next state logic
    always @(*) begin
        next_state = state;
        case (state)
            IDLE: begin
                if (start)
                    next_state = rw ? WRITE : READ;
            end
            
            WRITE: begin
                if (ram_ready)
                    next_state = DONE;
            end
            
            READ: begin
                if (ram_ready)
                    next_state = DONE;
            end
            
            DONE: begin
                if (!start)
                    next_state = IDLE;
            end
        endcase
    end

    // Output logic
    always @(posedge clk or posedge rst) begin
        if (rst) begin
            ram_wr_en <= 0;
            ram_rd_en <= 0;
            ram_addr <= 0;
            ram_data_in <= 0;
            read_data <= 0;
            done <= 0;
        end else begin
            case (state)
                IDLE: begin
                    ram_wr_en <= 0;
                    ram_rd_en <= 0;
                    done <= 0;
                end
                
                WRITE: begin
                    ram_wr_en <= 1;
                    ram_rd_en <= 0;
                    ram_addr <= address;
                    ram_data_in <= write_data;
                end
                
                READ: begin
                    ram_wr_en <= 0;
                    ram_rd_en <= 1;
                    ram_addr <= address;
                    read_data <= ram_data_out;
                end
                
                DONE: begin
                    ram_wr_en <= 0;
                    ram_rd_en <= 0;
                    done <= 1;
                end
            endcase
        end
    end

endmodule

rtl/top.v
module top #(
    parameter ADDR_WIDTH = 8,
    parameter DATA_WIDTH = 8,
    parameter DEPTH = 256
)(
    input wire clk,
    input wire rst,
    input wire start,
    input wire rw,
    input wire [ADDR_WIDTH-1:0] address,
    input wire [DATA_WIDTH-1:0] write_data,
    output wire [DATA_WIDTH-1:0] read_data,
    output wire done
);

    wire ram_wr_en, ram_rd_en, ram_ready;
    wire [ADDR_WIDTH-1:0] ram_addr;
    wire [DATA_WIDTH-1:0] ram_data_in, ram_data_out;

    ram_controller #(
        .ADDR_WIDTH(ADDR_WIDTH),
        .DATA_WIDTH(DATA_WIDTH)
    ) controller (
        .clk(clk),
        .rst(rst),
        .start(start),
        .rw(rw),
        .address(address),
        .write_data(write_data),
        .read_data(read_data),
        .done(done),
        .ram_wr_en(ram_wr_en),
        .ram_rd_en(ram_rd_en),
        .ram_addr(ram_addr),
        .ram_data_in(ram_data_in),
        .ram_data_out(ram_data_out),
        .ram_ready(ram_ready)
    );

    ram #(
        .ADDR_WIDTH(ADDR_WIDTH),
        .DATA_WIDTH(DATA_WIDTH),
        .DEPTH(DEPTH)
    ) memory (
        .clk(clk),
        .wr_en(ram_wr_en),
        .rd_en(ram_rd_en),
        .addr(ram_addr),
        .data_in(ram_data_in),
        .data_out(ram_data_out),
        .ready(ram_ready)
    );

endmodule

testbench/tb_top.v
`timescale 1ns/1ps

module tb_top;

    reg clk;
    reg rst;
    reg start;
    reg rw;
    reg [7:0] address;
    reg [7:0] write_data;
    wire [7:0] read_data;
    wire done;

    // Instantiate the top module
    top #(
        .ADDR_WIDTH(8),
        .DATA_WIDTH(8),
        .DEPTH(256)
    ) dut (
        .clk(clk),
        .rst(rst),
        .start(start),
        .rw(rw),
        .address(address),
        .write_data(write_data),
        .read_data(read_data),
        .done(done)
    );

    // Clock generation
    initial begin
        clk = 0;
        forever #5 clk = ~clk;  // 100MHz clock
    end

    // Dump waveforms
    initial begin
        $dumpfile("sim/ram_controller.vcd");
        $dumpvars(0, tb_top);
    end

    // Test sequence
    initial begin
        $display("=== RAM Controller Testbench ===");
        
        // Initialize
        rst = 1;
        start = 0;
        rw = 0;
        address = 0;
        write_data = 0;
        
        #20 rst = 0;
        
        // Test 1: Write to address 0x10
        $display("Test 1: Write 0xAB to address 0x10");
        #10;
        address = 8'h10;
        write_data = 8'hAB;
        rw = 1;
        start = 1;
        
        @(posedge done);
        #10 start = 0;
        $display("Write complete");
        
        // Test 2: Read from address 0x10
        #20;
        $display("Test 2: Read from address 0x10");
        address = 8'h10;
        rw = 0;
        start = 1;
        
        @(posedge done);
        $display("Read data: 0x%h (expected 0xAB)", read_data);
        #10 start = 0;
        
        // Test 3: Write to address 0x20
        #20;
        $display("Test 3: Write 0xCD to address 0x20");
        address = 8'h20;
        write_data = 8'hCD;
        rw = 1;
        start = 1;
        
        @(posedge done);
        #10 start = 0;
        $display("Write complete");
        
        // Test 4: Read from address 0x20
        #20;
        $display("Test 4: Read from address 0x20");
        address = 8'h20;
        rw = 0;
        start = 1;
        
        @(posedge done);
        $display("Read data: 0x%h (expected 0xCD)", read_data);
        #10 start = 0;
        
        // Test 5: Read from address 0x10 again
        #20;
        $display("Test 5: Read from address 0x10 again");
        address = 8'h10;
        rw = 0;
        start = 1;
        
        @(posedge done);
        $display("Read data: 0x%h (expected 0xAB)", read_data);
        #10 start = 0;
        
        #50;
        $display("=== All tests completed ===");
        $finish;
    end

    // Timeout
    initial begin
        #10000;
        $display("ERROR: Simulation timeout");
        $finish;
    end

endmodule

sim/ram_controller.vcd
$date
	Wed Dec 24 17:15:45 2025
$end
$version
	Icarus Verilog
$end
$timescale
	1ps
$end
$scope module tb_top $end
$var wire 8 ! read_data [7:0] $end
$var wire 1 " done $end
$var reg 8 # address [7:0] $end
$var reg 1 $ clk $end
$var reg 1 % rst $end
$var reg 1 & rw $end
$var reg 1 ' start $end
$var reg 8 ( write_data [7:0] $end
$scope module dut $end
$var wire 8 ) address [7:0] $end
$var wire 1 $ clk $end
$var wire 1 % rst $end
$var wire 1 & rw $end
$var wire 1 ' start $end
$var wire 8 * write_data [7:0] $end
$var wire 8 + read_data [7:0] $end
$var wire 1 , ram_wr_en $end
$var wire 1 - ram_ready $end
$var wire 1 . ram_rd_en $end
$var wire 8 / ram_data_out [7:0] $end
$var wire 8 0 ram_data_in [7:0] $end
$var wire 8 1 ram_addr [7:0] $end
$var wire 1 " done $end
$scope module controller $end
$var wire 8 2 address [7:0] $end
$var wire 1 $ clk $end
$var wire 1 % rst $end
$var wire 1 & rw $end
$var wire 1 ' start $end
$var wire 8 3 write_data [7:0] $end
$var wire 1 - ram_ready $end
$var wire 8 4 ram_data_out [7:0] $end
$var reg 1 " done $end
$var reg 2 5 next_state [1:0] $end
$var reg 8 6 ram_addr [7:0] $end
$var reg 8 7 ram_data_in [7:0] $end
$var reg 1 . ram_rd_en $end
$var reg 1 , ram_wr_en $end
$var reg 8 8 read_data [7:0] $end
$var reg 2 9 state [1:0] $end
$upscope $end
$scope module memory $end
$var wire 8 : addr [7:0] $end
$var wire 1 $ clk $end
$var wire 8 ; data_in [7:0] $end
$var wire 1 . rd_en $end
$var wire 1 , wr_en $end
$var reg 8 < data_out [7:0] $end
$var reg 1 - ready $end
$var integer 32 = i [31:0] $end
$upscope $end
$upscope $end
$upscope $end
$enddefinitions $end
#0
$dumpvars
b100000000 =
bx <
b0 ;
b0 :
b0 9
b0 8
b0 7
b0 6
b0 5
bx 4
b0 3
b0 2
b0 1
b0 0
bx /
0.
x-
0,
b0 +
b0 *
b0 )
b0 (
0'
0&
1%
0$
b0 #
0"
b0 !
$end
#5000
0-
1$
#10000
0$
#15000
1$
#20000
0$
0%
#25000
1$
#30000
b1 5
0$
1'
1&
b10101011 (
b10101011 *
b10101011 3
b10000 #
b10000 )
b10000 2
#35000
b1 9
1$
#40000
0$
#45000
b10101011 0
b10101011 7
b10101011 ;
b10000 1
b10000 6
b10000 :
1,
1$
#50000
0$
#55000
b11 5
1-
1$
#60000
0$
#65000
b11 9
1-
1$
#70000
0$
#75000
1"
0,
1-
1$
#80000
0$
#85000
b0 9
0-
b0 5
1$
0'
#90000
0$
#95000
0"
1$
#100000
0$
#105000
b10 9
b10 5
1$
1'
0&
#110000
0$
#115000
bx !
bx +
bx 8
1.
1$
#120000
0$
#125000
b11 5
1-
b10101011 /
b10101011 4
b10101011 <
1$
#130000
0$
#135000
b11 9
b10101011 !
b10101011 +
b10101011 8
1-
1$
#140000
0$
#145000
1"
0.
1-
1$
#150000
0$
#155000
b0 9
0-
b0 5
1$
0'
#160000
0$
#165000
0"
1$
#170000
0$
#175000
b1 9
b1 5
1$
1'
1&
b11001101 (
b11001101 *
b11001101 3
b100000 #
b100000 )
b100000 2
#180000
0$
#185000
b11001101 0
b11001101 7
b11001101 ;
b100000 1
b100000 6
b100000 :
1,
1$
#190000
0$
#195000
b11 5
1-
1$
#200000
0$
#205000
b11 9
1-
1$
#210000
0$
#215000
1"
0,
1-
1$
#220000
0$
#225000
b0 9
0-
b0 5
1$
0'
#230000
0$
#235000
0"
1$
#240000
0$
#245000
b10 9
b10 5
1$
1'
0&
#250000
0$
#255000
1.
1$
#260000
0$
#265000
b11 5
1-
b11001101 /
b11001101 4
b11001101 <
1$
#270000
0$
#275000
b11 9
b11001101 !
b11001101 +
b11001101 8
1-
1$
#280000
0$
#285000
1"
0.
1-
1$
#290000
0$
#295000
b0 9
0-
b0 5
1$
0'
#300000
0$
#305000
0"
1$
#310000
0$
#315000
b10 9
b10 5
1$
1'
b10000 #
b10000 )
b10000 2
#320000
0$
#325000
b10000 1
b10000 6
b10000 :
1.
1$
#330000
0$
#335000
b11 5
1-
b10101011 /
b10101011 4
b10101011 <
1$
#340000
0$
#345000
b10101011 !
b10101011 +
b10101011 8
b11 9
1-
1$
#350000
0$
#355000
1"
0.
1-
1$
#360000
0$
#365000
b0 9
0-
b0 5
1$
0'
#370000
0$
#375000
0"
1$
